gmail_mcp/__init__.py
gmail_mcp/__main__.py
gmail_mcp/auth.py
gmail_mcp/gmail_client.py
gmail_mcp/server.py
mcp_gmail_reader-0.1.0.dist-info/METADATA
mcp_gmail_reader-0.1.0.dist-info/WHEEL
mcp_gmail_reader-0.1.0.dist-info/licenses/LICENSE
mcp_gmail_reader-0.1.0.dist-info/RECORD
