Metadata-Version: 2.4
Name: mcp-gmail-reader
Version: 0.1.0
Summary: MCP server for Gmail - search emails, read messages, download attachments
Project-URL: Homepage, https://github.com/Maheidem/gmail-mcp
Project-URL: Repository, https://github.com/Maheidem/gmail-mcp
Project-URL: Issues, https://github.com/Maheidem/gmail-mcp/issues
Author: Marcos Heidemann
License-Expression: MIT
License-File: LICENSE
Keywords: ai,claude,email,gmail,mcp,model-context-protocol
Classifier: Development Status :: 4 - Beta
Classifier: Intended Audience :: Developers
Classifier: License :: OSI Approved :: MIT License
Classifier: Programming Language :: Python :: 3
Classifier: Programming Language :: Python :: 3.10
Classifier: Programming Language :: Python :: 3.11
Classifier: Programming Language :: Python :: 3.12
Classifier: Programming Language :: Python :: 3.13
Requires-Python: >=3.10
Requires-Dist: google-api-python-client
Requires-Dist: google-auth-httplib2
Requires-Dist: google-auth-oauthlib
Requires-Dist: mcp[cli]
